cyberian/__init__.py
cyberian/_version.py
cyberian/agent_client.py
cyberian/cli.py
cyberian/dashboard_config.py
cyberian/models.py
cyberian/runner.py
cyberian/server_utils.py
cyberian-0.2.1.dist-info/METADATA
cyberian-0.2.1.dist-info/WHEEL
cyberian-0.2.1.dist-info/entry_points.txt
cyberian-0.2.1.dist-info/licenses/LICENSE
cyberian-0.2.1.dist-info/RECORD
