Metadata-Version: 2.4
Name: cyberian
Version: 0.2.1
Summary: Wrapper for agentapi for pipelines
Author-email: My Name <my-name@my-org.org>
License-Expression: BSD-3-Clause
License-File: LICENSE
Requires-Python: <4.0,>=3.11
Requires-Dist: httpx>=0.27.0
Requires-Dist: jinja2>=3.1.6
Requires-Dist: linkml-runtime>=1.9.4
Requires-Dist: pydantic>=2.12.3
Requires-Dist: pyyaml>=6.0
Requires-Dist: typer>=0.9.0
Provides-Extra: providers
Requires-Dist: deep-research-client>=0.1.0; extra == 'providers'
